{
  "project_info": {
    "project_number": "831546059578",
    "firebase_url": "https://nyererefy-3dcad.firebaseio.com",
    "project_id": "nyererefy-3dcad",
    "storage_bucket": "nyererefy-3dcad.appspot.com"
  },
  "client": [
    {
      "client_info": {
        "mobilesdk_app_id": "1:831546059578:android:38d2a0ee422e105c21fe03",
        "android_client_info": {
          "package_name": "com.nyererefy"
        }
      },
      "oauth_client": [
        {
          "client_id": "831546059578-8c954ndpmvqca9dhmqk8prpurm8d827m.apps.googleusercontent.com",
          "client_type": 3
        }
      ],
      "api_key": [
        {
          "current_key": "AIzaSyBka0BiKw0IV-kM5Nx8voYAvjDd4vWXmBU"
        }
      ],
      "services": {
        "appinvite_service": {
          "other_platform_oauth_client": [
            {
              "client_id": "831546059578-8c954ndpmvqca9dhmqk8prpurm8d827m.apps.googleusercontent.com",
              "client_type": 3
            }
          ]
        }
      }
    }
  ],
  "configuration_version": "1"
}